dynamon/__init__.py
dynamon/dynamon.py
dynamon-0.1.1.dist-info/DESCRIPTION.rst
dynamon-0.1.1.dist-info/METADATA
dynamon-0.1.1.dist-info/RECORD
dynamon-0.1.1.dist-info/WHEEL
dynamon-0.1.1.dist-info/metadata.json
dynamon-0.1.1.dist-info/top_level.txt
