Metadata-Version: 2.0
Name: dynamon
Version: 0.1.1
Summary: Python API for dynamon.io
Home-page: https://github.com/dynamon-io/dynamon-python
Author: Viktor Qvarfordt
Author-email: viktor.qvarfordt@gmail.com
License: UNKNOWN
Platform: UNKNOWN
Requires-Dist: requests
